to_cloud_run.py
to_cloud_run-1.6.dist-info/METADATA
to_cloud_run-1.6.dist-info/WHEEL
to_cloud_run-1.6.dist-info/entry_points.txt
to_cloud_run-1.6.dist-info/top_level.txt
to_cloud_run-1.6.dist-info/RECORD
