Metadata-Version: 2.1
Name: to-cloud-run
Version: 1.6
Summary: UNKNOWN
Home-page: UNKNOWN
License: UNKNOWN
Platform: UNKNOWN
Requires-Dist: python-dotenv
